[
  {
    "name": "Nike Air Force 1 '07 LV8",
    "price": "119,99 €",
    "image": null,
    "link": "https://www.nike.com/fr/t/chaussure-air-force-1-07-lv8-pour-vO72tFNp/IB6388-003",
    "brand": "Nike"
  },
  {
    "name": "Nike Shox TL",
    "price": "169,99 €",
    "image": null,
    "link": "https://www.nike.com/fr/t/chaussure-shox-tl-pour-xFMK4kAG/AV3595-002",
    "brand": "Nike"
  },
  {
    "name": "Nike Ava Rover",
    "price": "139,99 €",
    "image": null,
    "link": "https://www.nike.com/fr/t/chaussure-ava-rover-lJnNmF/DX4215-204",
    "brand": "Nike"
  },
  {
    "name": "Nike Air Force 1 '07 LV8",
    "price": "129,99 €",
    "image": null,
    "link": "https://www.nike.com/fr/t/chaussure-air-force-1-07-lv8-7Yep4ozV/IH4452-001",
    "brand": "Nike"
  },
  {
    "name": "Nike Air Force 1 '07",
    "price": "129,99 €",
    "image": null,
    "link": "https://www.nike.com/fr/t/chaussure-air-force-1-07-pour-Lm8qpbC9/IH7332-001",
    "brand": "Nike"
  },
  {
    "name": "Air Jordan 4 Retro « Cave Stone and Black »",
    "price": "209,99 €",
    "image": null,
    "link": "https://www.nike.com/fr/t/chaussure-air-jordan-4-retro-cave-stone-and-black-pour-HtLkgl/FV5029-200",
    "brand": "Nike"
  },
  {
    "name": "Nike Pegasus Premium",
    "price": "209,99 €",
    "image": null,
    "link": "https://www.nike.com/fr/t/chaussure-de-running-sur-route-pegasus-pour-DRPOJVUu/II6308-600",
    "brand": "Nike"
  },
  {
    "name": "Nike Air Max Plus 3",
    "price": "189,99 €",
    "image": null,
    "link": "https://www.nike.com/fr/t/chaussure-air-max-plus-3-pour-2WxEl2Ed/CW1417-100",
    "brand": "Nike"
  },
  {
    "name": "Nike Pegasus Premium LV8",
    "price": "209,99 €",
    "image": null,
    "link": "https://www.nike.com/fr/t/chaussure-de-running-sur-route-pegasus-lv8-pour-DK3cCPMs/IH3256-700",
    "brand": "Nike"
  },
  {
    "name": "Nike Air Max 95 « Big Bubble »",
    "price": "189,99 €",
    "image": null,
    "link": "https://www.nike.com/fr/t/chaussure-air-max-95-big-bubble-pour-cbxu16ox/HM8755-001",
    "brand": "Nike"
  },
  {
    "name": "Nike P-6000 « Denim »",
    "price": "119,99 €",
    "image": null,
    "link": "https://www.nike.com/fr/t/chaussure-p-6000-denim-pour-dgeUbrfj/IH3646-499",
    "brand": "Nike"
  },
  {
    "name": "Nike Dunk Low Retro",
    "price": "119,99 €",
    "image": null,
    "link": "https://www.nike.com/fr/t/chaussures-dunk-low-retro-pour-RmcsMK03/HF5441-107",
    "brand": "Nike"
  },
  {
    "name": "Nike Court Vision Low Next Nature",
    "price": "79,99 €",
    "image": null,
    "link": "https://www.nike.com/fr/t/chaussure-court-vision-low-next-nature-pour-a57TM6qB/DH2987-100",
    "brand": "Nike"
  },
  {
    "name": "Nike Air Force 1 Low Retro Premium",
    "price": "139,99 €",
    "image": null,
    "link": "https://www.nike.com/fr/t/chaussure-air-force-1-low-retro-pour-XHrVOGry/IM3078-100",
    "brand": "Nike"
  },
  {
    "name": "Nike Air Max Plus",
    "price": "199,99 €",
    "image": null,
    "link": "https://www.nike.com/fr/t/chaussure-air-max-plus-WWM1O4Lz/IH4458-001",
    "brand": "Nike"
  },
  {
    "name": "Nike Air Max Waffle SP",
    "price": "139,99 €",
    "image": null,
    "link": "https://www.nike.com/fr/t/chaussure-air-max-waffle-sp-pour-PUTesdWW/IM0340-300",
    "brand": "Nike"
  },
  {
    "name": "Nike Dunk Low Retro SE",
    "price": "119,99 €",
    "image": null,
    "link": "https://www.nike.com/fr/t/chaussure-dunk-low-retro-se-pour-Br7SQvD7/IB2990-100",
    "brand": "Nike"
  },
  {
    "name": "Nike Air Force 1 Luxe",
    "price": "139,99 €",
    "image": null,
    "link": "https://www.nike.com/fr/t/chaussures-air-force-1-luxe-pour-ZyIrJFlT/DD9605-100",
    "brand": "Nike"
  },
  {
    "name": "Nike Air Max Alpha Trainer 6",
    "price": "89,99 €",
    "image": null,
    "link": "https://www.nike.com/fr/t/chaussure-dentrainement-air-max-alpha-trainer-6-pour-4RnBJ0/FQ1833-003",
    "brand": "Nike"
  },
  {
    "name": "Nike Air Zoom Spiridon Cage 2",
    "price": "169,99 €",
    "image": null,
    "link": "https://www.nike.com/fr/t/chaussure-air-zoom-spiridon-cage-2-pour-aqdu7l9L/HM8497-010",
    "brand": "Nike"
  },
  {
    "name": "Jordan Spizike Low",
    "price": "169,99 €",
    "image": null,
    "link": "https://www.nike.com/fr/t/chaussure-jordan-spizike-low-pour-S1JYZpUo/IM2176-133",
    "brand": "Nike"
  },
  {
    "name": "Nike Air Max 90",
    "price": "149,99 €",
    "image": null,
    "link": "https://www.nike.com/fr/t/chaussure-air-max-90-pour-GHOqOQoI/CN8490-100",
    "brand": "Nike"
  },
  {
    "name": "Nike Air Max SC",
    "price": "89,99 €",
    "image": null,
    "link": "https://www.nike.com/fr/t/chaussure-air-max-sc-pour-DCCKUzIJ/CW4555-003",
    "brand": "Nike"
  },
  {
    "name": "Tatum 3 « Tie Dye »",
    "price": "129,99 €",
    "image": null,
    "link": "https://www.nike.com/fr/t/chaussure-de-basket-tatum-3-tie-dye-qxNiW2Ot/FZ6598-400",
    "brand": "Nike"
  },
  {
    "name": "Nike Zoom Vomero 5",
    "price": "159,99 €",
    "image": null,
    "link": "https://www.nike.com/fr/t/chaussure-zoom-vomero-5-pour-gzqpHQ/BV1358-003",
    "brand": "Nike"
  },
  {
    "name": "Jordan Heir Series",
    "price": "109,99 €",
    "image": null,
    "link": "https://www.nike.com/fr/t/chaussure-de-basket-jordan-heir-series-gJSoFD9d/IO0409-108",
    "brand": "Nike"
  },
  {
    "name": "Nike Shox R4",
    "price": "149,99 €",
    "image": null,
    "link": "https://www.nike.com/fr/t/chaussure-shox-r4-pour-IUejfqaZ/HQ1988-101",
    "brand": "Nike"
  },
  {
    "name": "Nike React Vision",
    "price": "139,99 €",
    "image": null,
    "link": "https://www.nike.com/fr/t/chaussure-react-vision-pour-5VK6r1/CD4373-004",
    "brand": "Nike"
  },
  {
    "name": "Paris Saint-Germain Air Max Plus Premium",
    "price": "199,99 €",
    "image": null,
    "link": "https://www.nike.com/fr/t/chaussure-paris-saint-germain-air-max-plus-pour-L3Bnhluw/IB2253-001",
    "brand": "Nike"
  },
  {
    "name": "Air Jordan 1 Low Premium",
    "price": "139,99 €",
    "image": null,
    "link": "https://www.nike.com/fr/t/chaussure-air-jordan-1-low-pour-Fwn1m6cN/IB8058-110",
    "brand": "Nike"
  },
  {
    "name": "Nike Air Force 1 '07 LV8",
    "price": "129,99 €",
    "image": null,
    "link": "https://www.nike.com/fr/t/chaussure-air-force-1-07-lv8-pour-9O3Az8Sc/II7630-100",
    "brand": "Nike"
  },
  {
    "name": "Nike Tiempo Legend 10 Club",
    "price": "54,99 €",
    "image": null,
    "link": "https://www.nike.com/fr/t/chaussure-de-foot-basse-a-crampons-multi-surfaces-tiempo-legend-10-club-zfeDslCY/DV4344-003",
    "brand": "Nike"
  },
  {
    "name": "Nike Zoom Vomero 5",
    "price": "159,99 €",
    "image": null,
    "link": "https://www.nike.com/fr/t/chaussure-zoom-vomero-5-pour-K3gvQuL5/HF1553-101",
    "brand": "Nike"
  },
  {
    "name": "Nike Zoom Vomero 5",
    "price": "159,99 €",
    "image": null,
    "link": "https://www.nike.com/fr/t/chaussure-zoom-vomero-5-pour-q85lkg/FB9149-005",
    "brand": "Nike"
  },
  {
    "name": "Nike Pegasus 41 SE",
    "price": "149,99 €",
    "image": null,
    "link": "https://www.nike.com/fr/t/chaussure-de-running-sur-route-pegasus-41-se-pour-5WbXfh/IH3583-999",
    "brand": "Nike"
  },
  {
    "name": "Nike Air Max Dn8",
    "price": "189,99 €",
    "image": null,
    "link": "https://www.nike.com/fr/t/chaussure-air-max-dn8-pour-2U281Cg7/FQ7860-001",
    "brand": "Nike"
  },
  {
    "name": "Nike Air Max Dn",
    "price": "169,99 €",
    "image": null,
    "link": "https://www.nike.com/fr/t/chaussure-air-max-dn-pour-wKxzvjH9/IH4463-001",
    "brand": "Nike"
  },
  {
    "name": "Luka 4 « Light Orewood and Tangerine »",
    "price": "129,99 €",
    "image": null,
    "link": "https://www.nike.com/fr/t/chaussure-de-basket-luka-4-light-orewood-and-tangerine-IAbf2mix/IO0202-100",
    "brand": "Nike"
  },
  {
    "name": "Nike Air Force 1 Flyknit 2.0",
    "price": "119,99 €",
    "image": null,
    "link": "https://www.nike.com/fr/t/chaussure-air-force-1-flyknit-2-7EHtWGRa/AV3042-001",
    "brand": "Nike"
  },
  {
    "name": "Nike Air Max 90 Essential+",
    "price": "149,99 €",
    "image": null,
    "link": "https://www.nike.com/fr/t/chaussure-air-max-90-essential-pour-B9fcPXcl/IH2063-201",
    "brand": "Nike"
  },
  {
    "name": "Nike Air Max Plus",
    "price": "199,99 €",
    "image": null,
    "link": "https://www.nike.com/fr/t/chaussure-air-max-plus-pour-ZAmZMX9P/IH4459-025",
    "brand": "Nike"
  },
  {
    "name": "Nike V5 RNR",
    "price": "84,99 €",
    "image": null,
    "link": "https://www.nike.com/fr/t/chaussure-v5-rnr-pour-rAnbXJ7w/HJ5228-001",
    "brand": "Nike"
  },
  {
    "name": "Air Jordan 4RM",
    "price": "149,99 €",
    "image": null,
    "link": "https://www.nike.com/fr/t/chaussure-air-jordan-4rm-9oPLQrjD/IH4488-072",
    "brand": "Nike"
  },
  {
    "name": "Nike Pegasus 41",
    "price": "149,99 €",
    "image": null,
    "link": "https://www.nike.com/fr/t/chaussure-de-running-sur-route-pegasus-41-pour-Jdn3qq/IH4455-047",
    "brand": "Nike"
  },
  {
    "name": "Nike SB Dunk Low Pro B",
    "price": "119,99 €",
    "image": null,
    "link": "https://www.nike.com/fr/t/chaussure-de-skate-sb-dunk-low-pro-b-ejd664Do/HJ0367-301",
    "brand": "Nike"
  },
  {
    "name": "Nike Calm",
    "price": "49,99 €",
    "image": null,
    "link": "https://www.nike.com/fr/t/claquette-calm-pour-qwJcjE6C/FD4116-001",
    "brand": "Nike"
  },
  {
    "name": "Air Jordan 1 Low SE",
    "price": "139,99 €",
    "image": null,
    "link": "https://www.nike.com/fr/t/chaussure-air-jordan-1-low-se-pour-cmqWCOkT/IB7692-400",
    "brand": "Nike"
  },
  {
    "name": "Nike Cortez Leather",
    "price": "99,99 €",
    "image": null,
    "link": "https://www.nike.com/fr/t/chaussure-cortez-leather-pour-5lNXZq/DM4044-105",
    "brand": "Nike"
  },
  {
    "name": "Nike SB Dunk Low Pro",
    "price": "119,99 €",
    "image": null,
    "link": "https://www.nike.com/fr/t/chaussures-de-skateboard-sb-dunk-low-pro-W9cHC7/HF3704-100",
    "brand": "Nike"
  },
  {
    "name": "Nike Dunk Low Retro SE",
    "price": "119,99 €",
    "image": null,
    "link": "https://www.nike.com/fr/t/chaussure-dunk-low-retro-se-pour-MdAUTl2o/IB6399-002",
    "brand": "Nike"
  },
  {
    "name": "Nike Air Force 1 '07",
    "price": "129,99 €",
    "image": null,
    "link": "https://www.nike.com/fr/t/chaussure-air-force-1-07-pour-naKHSECK/IH4461-100",
    "brand": "Nike"
  },
  {
    "name": "Nike Revolution 8",
    "price": "64,99 €",
    "image": null,
    "link": "https://www.nike.com/fr/t/chaussure-de-running-sur-route-revolution-8-pour-JRd2QU3H/HQ1996-100",
    "brand": "Nike"
  },
  {
    "name": "Nike Mercurial Superfly 10 Academy",
    "price": "94,99 €",
    "image": null,
    "link": "https://www.nike.com/fr/t/chaussure-de-foot-a-crampons-montante-multi-surfaces-mercurial-superfly-10-academy-u2h1JwR4/FQ1456-001",
    "brand": "Nike"
  },
  {
    "name": "Air Jordan 1 Mid SE",
    "price": "149,99 €",
    "image": null,
    "link": "https://www.nike.com/fr/t/chaussure-air-jordan-1-mid-se-pour-OlK8d2p4/HQ2011-100",
    "brand": "Nike"
  },
  {
    "name": "Jordan Spizike Low SE",
    "price": "179,99 €",
    "image": null,
    "link": "https://www.nike.com/fr/t/chaussure-jordan-spizike-low-se-pour-o61P74J9/IM7425-004",
    "brand": "Nike"
  },
  {
    "name": "Nike SB Force 58",
    "price": "74,99 €",
    "image": null,
    "link": "https://www.nike.com/fr/t/chaussure-de-skateboard-sb-force-58-9Uwp4KFl/IH0636-141",
    "brand": "Nike"
  },
  {
    "name": "Nike Offcourt Adjust",
    "price": "44,99 €",
    "image": null,
    "link": "https://www.nike.com/fr/t/claquette-offcourt-adjust-pour-W7Gq0r/DQ9624-001",
    "brand": "Nike"
  },
  {
    "name": "Kobe IX Elite Low EM Protro",
    "price": "179,99 €",
    "image": null,
    "link": "https://www.nike.com/fr/t/chaussure-de-basket-kobe-ix-elite-low-em-protro-Zf6uU4bF/IH1401-002",
    "brand": "Nike"
  },
  {
    "name": "Nike Cortez Textile",
    "price": "89,99 €",
    "image": null,
    "link": "https://www.nike.com/fr/t/chaussure-cortez-textile-pour-Yb4aFcxN/DZ2795-001",
    "brand": "Nike"
  },
  {
    "name": "Air Jordan 1 Mid",
    "price": "139,99 €",
    "image": null,
    "link": "https://www.nike.com/fr/t/chaussure-air-jordan-1-mid-QJTvQh/554724-136",
    "brand": "Nike"
  },
  {
    "name": "Air Jordan 1 High OG « Rare Air »",
    "price": "189,99 €",
    "image": null,
    "link": "https://www.nike.com/fr/t/chaussure-air-jordan-1-high-og-rare-air-pour-PM5PZ09R/DB4612-100",
    "brand": "Nike"
  },
  {
    "name": "Nike SB Dunk Low Pro",
    "price": "119,99 €",
    "image": null,
    "link": "https://www.nike.com/fr/t/chaussures-de-skateboard-sb-dunk-low-pro-4peTLd6z/HJ4135-600",
    "brand": "Nike"
  },
  {
    "name": "Nike Victori One",
    "price": "34,99 €",
    "image": null,
    "link": "https://www.nike.com/fr/t/claquette-victori-one-pour-m8lQTL/CN9675-002",
    "brand": "Nike"
  },
  {
    "name": "A'One ASW",
    "price": "119,99 €",
    "image": null,
    "link": "https://www.nike.com/fr/t/chaussure-de-basket-aja-wilson-aone-asw-HkxAm749/HQ1728-001",
    "brand": "Nike"
  },
  {
    "name": "Giannis Freak 7 « Ignition »",
    "price": "114,99 €",
    "image": null,
    "link": "https://www.nike.com/fr/t/chaussure-de-basket-giannis-freak-7-ignition-7DesDuvY/HF3450-800",
    "brand": "Nike"
  },
  {
    "name": "KD18 « Unfinished »",
    "price": "169,99 €",
    "image": null,
    "link": "https://www.nike.com/fr/t/chaussure-de-basket-kd18-unfinished-SpIHLla2/IM5843-500",
    "brand": "Nike"
  },
  {
    "name": "Nike Phantom 6 Low Elite « Erling Haaland »",
    "price": "279,99 €",
    "image": null,
    "link": "https://www.nike.com/fr/t/crampons-de-foot-phantom-6-low-elite-erling-haaland-pour-terrain-sec-Q3AzuO8P/HQ2332-800",
    "brand": "Nike"
  },
  {
    "name": "Giannis Freak 7 « Live Wire »",
    "price": "114,99 €",
    "image": null,
    "link": "https://www.nike.com/fr/t/chaussure-de-basket-giannis-freak-7-live-wire-w7MvXX4a/HQ1743-600",
    "brand": "Nike"
  },
  {
    "name": "Nike Mercurial Vapor 16 Elite x Air Max 95 SE",
    "price": "299,99 €",
    "image": null,
    "link": "https://www.nike.com/fr/t/chaussure-de-foot-basse-a-crampons-fg-mercurial-vapor-16-elite-air-max-95-se-ksi9P9rH/HV9915-100",
    "brand": "Nike"
  },
  {
    "name": "Nike Phantom 6 Low Elite",
    "price": "279,99 €",
    "image": null,
    "link": "https://www.nike.com/fr/t/crampons-de-foot-phantom-6-low-elite-pour-terrain-sec-HXntJq36/IH3737-001",
    "brand": "Nike"
  },
  {
    "name": "Nike Mercurial Superfly 10 Elite « Sam Kerr »",
    "price": "289,99 €",
    "image": null,
    "link": "https://www.nike.com/fr/t/crampons-de-foot-a-coupe-montante-pour-terrain-sec-mercurial-superfly-10-elite-sam-kerr-Sq7OzJ4R/HV8859-100",
    "brand": "Nike"
  },
  {
    "name": "Nike Mercurial Superfly 10 Academy LV8",
    "price": "99,99 €",
    "image": null,
    "link": "https://www.nike.com/fr/t/crampons-de-foot-multi-surfaces-a-coupe-montante-mercurial-superfly-10-academy-lv8-qagwd6sa/HJ7311-600",
    "brand": "Nike"
  },
  {
    "name": "Nike Phantom 6 High Academy",
    "price": "94,99 €",
    "image": null,
    "link": "https://www.nike.com/fr/t/crampons-de-foot-multi-surfaces-phantom-6-high-academy-kT9YHHUj/HQ2278-003",
    "brand": "Nike"
  },
  {
    "name": "Nike Mercurial Superfly 10 Elite",
    "price": "279,99 €",
    "image": null,
    "link": "https://www.nike.com/fr/t/chaussure-de-foot-montante-a-crampons-mercurial-superfly-10-elite-R64fN3nv/FQ1454-600",
    "brand": "Nike"
  },
  {
    "name": "Nike Phantom 6 Low Elite « Erling Haaland »",
    "price": "279,99 €",
    "image": null,
    "link": "https://www.nike.com/fr/t/crampons-de-foot-pour-terrain-synthetique-phantom-6-low-elite-erling-haaland-rDc3Sgfe/IH1784-800",
    "brand": "Nike"
  },
  {
    "name": "Nike Pegasus 41",
    "price": "139,99 €",
    "image": null,
    "link": "https://www.nike.com/fr/t/chaussure-de-running-sur-route-pegasus-41-pour-nTscgBsq/FN4932-007",
    "brand": "Nike"
  },
  {
    "name": "Air Jordan 4 RM",
    "price": "149,99 €",
    "image": null,
    "link": "https://www.nike.com/fr/t/chaussure-air-jordan-4-rm-pour-F87aIyJZ/FQ7939-110",
    "brand": "Nike"
  },
  {
    "name": "Giannis Immortality 4",
    "price": "89,99 €",
    "image": null,
    "link": "https://www.nike.com/fr/t/chaussure-de-basket-giannis-immortality-4-x5GjZ5/FQ3680-800",
    "brand": "Nike"
  },
  {
    "name": "LeBron XXII",
    "price": "189,99 €",
    "image": null,
    "link": "https://www.nike.com/fr/t/chaussure-de-basket-lebron-xxii-PzdHqMLW/HV8451-400",
    "brand": "Nike"
  },
  {
    "name": "Nike Mercurial Superfly 10 Academy",
    "price": "99,99 €",
    "image": null,
    "link": "https://www.nike.com/fr/t/chaussure-de-foot-montante-a-crampons-sg-pro-mercurial-superfly-10-academy-8rQGpp/FQ8336-600",
    "brand": "Nike"
  },
  {
    "name": "Air Jordan 1 High OG « Rare Air »",
    "price": "189,99 €",
    "image": null,
    "link": "https://www.nike.com/fr/t/chaussure-air-jordan-1-high-og-rare-air-pour-oSRhapAE/DZ5485-100",
    "brand": "Nike"
  },
  {
    "name": "Nike Mercurial Superfly 10 Academy",
    "price": "94,99 €",
    "image": null,
    "link": "https://www.nike.com/fr/t/chaussure-de-foot-montante-a-crampons-ag-mercurial-superfly-10-academy-Dz05x0/FQ8329-001",
    "brand": "Nike"
  },
  {
    "name": "Nike Vaporfly 4",
    "price": "259,99 €",
    "image": null,
    "link": "https://www.nike.com/fr/t/chaussure-de-course-sur-route-vaporfly-4-pour-0HnvEyVd/HF6414-101",
    "brand": "Nike"
  },
  {
    "name": "Nike Shox TL",
    "price": "169,99 €",
    "image": null,
    "link": "https://www.nike.com/fr/t/chaussure-shox-tl-pour-49WI75AK/IF6202-002",
    "brand": "Nike"
  },
  {
    "name": "Nike Run Defy",
    "price": "59,99 €",
    "image": null,
    "link": "https://www.nike.com/fr/t/chaussure-de-running-sur-route-run-defy-pour-015L9V/HM9594-002",
    "brand": "Nike"
  },
  {
    "name": "Nike Phantom 6 Low Elite",
    "price": "279,99 €",
    "image": null,
    "link": "https://www.nike.com/fr/t/crampons-de-foot-phantom-6-low-elite-pour-terrain-sec-4JpsnxJ9/HQ2331-400",
    "brand": "Nike"
  },
  {
    "name": "KD18",
    "price": "159,99 €",
    "image": null,
    "link": "https://www.nike.com/fr/t/chaussures-de-basket-kd18-ZdeQ9gbC/IM0634-105",
    "brand": "Nike"
  },
  {
    "name": "Air Jordan 1 Retro Low",
    "price": "149,99 €",
    "image": null,
    "link": "https://www.nike.com/fr/t/chaussure-sans-swoosh-air-jordan-1-retro-low-pour-bN72Ej/872782-100",
    "brand": "Nike"
  },
  {
    "name": "Nike Vomero 18",
    "price": "159,99 €",
    "image": null,
    "link": "https://www.nike.com/fr/t/chaussure-de-running-sur-route-vomero-18-pour-ZD23Xj/IH4454-001",
    "brand": "Nike"
  },
  {
    "name": "Nike Mercurial Vapor 16 Elite",
    "price": "279,99 €",
    "image": null,
    "link": "https://www.nike.com/fr/t/chaussure-de-foot-a-crampons-basse-fg-mercurial-vapor-16-elite-nnbTGr2z/HJ7325-600",
    "brand": "Nike"
  },
  {
    "name": "Nike Air Max 90 Drift",
    "price": "149,99 €",
    "image": null,
    "link": "https://www.nike.com/fr/t/chaussure-air-max-90-drift-pour-LFJe9cpW/HQ1416-001",
    "brand": "Nike"
  },
  {
    "name": "Nike Air Zoom Spiridon Cage 2",
    "price": "169,99 €",
    "image": null,
    "link": "https://www.nike.com/fr/t/chaussure-air-zoom-spiridon-cage-2-pour-LHJHcoT0/CJ1288-100",
    "brand": "Nike"
  },
  {
    "name": "Nike Air Max Plus",
    "price": "189,99 €",
    "image": null,
    "link": "https://www.nike.com/fr/t/chaussure-air-max-plus-pour-QcD8W0W2/DM0032-701",
    "brand": "Nike"
  },
  {
    "name": "Nike Precision 7",
    "price": "74,99 €",
    "image": null,
    "link": "https://www.nike.com/fr/t/chaussure-de-basket-precision-7-ypV5QMd3/HJ9153-100",
    "brand": "Nike"
  },
  {
    "name": "Nike Air Max TL 2.5",
    "price": "179,99 €",
    "image": null,
    "link": "https://www.nike.com/fr/t/chaussure-air-max-tl-2-5-pour-QCecVWDF/HM8818-001",
    "brand": "Nike"
  },
  {
    "name": "Air Jordan 5 Retro « Fire Red Black Tongue »",
    "price": "209,99 €",
    "image": null,
    "link": "https://www.nike.com/fr/t/chaussure-air-jordan-5-retro-fire-red-black-tongue-pour-qUtJBbwU/HQ7978-101",
    "brand": "Nike"
  },
  {
    "name": "Nike P-6000 Premium",
    "price": "119,99 €",
    "image": null,
    "link": "https://www.nike.com/fr/t/chaussure-p-6000-pour-OUU4WGqE/HJ7284-072",
    "brand": "Nike"
  },
  {
    "name": "Nike P-6000",
    "price": "109,99 €",
    "image": null,
    "link": "https://www.nike.com/fr/t/chaussure-p-6000-RqKVWQgs/FD9876-101",
    "brand": "Nike"
  },
  {
    "name": "Nike Air Max Muse",
    "price": "159,99 €",
    "image": null,
    "link": "https://www.nike.com/fr/t/chaussure-air-max-muse-pour-FhA5rstJ/FV1920-001",
    "brand": "Nike"
  },
  {
    "name": "Nike Air Max Moto 2K",
    "price": "129,99 €",
    "image": null,
    "link": "https://www.nike.com/fr/t/chaussures-air-max-moto-2k-pour-Nbabhz8p/HQ2056-103",
    "brand": "Nike"
  },
  {
    "name": "Nike Shox TL",
    "price": "169,99 €",
    "image": null,
    "link": "https://www.nike.com/fr/t/chaussure-shox-tl-pour-BbQXjBAC/AR3566-002",
    "brand": "Nike"
  },
  {
    "name": "Nike P-6000 By You",
    "price": "139,99 €",
    "image": null,
    "link": "https://www.nike.com/fr/u/custom-nike-p-6000-by-you-10002088/4921614937",
    "brand": "Nike"
  },
  {
    "name": "Nike Air Superfly",
    "price": "99,99 €",
    "image": null,
    "link": "https://www.nike.com/fr/t/chaussure-air-superfly-pour-Gra217Z0/IB5824-700",
    "brand": "Nike"
  },
  {
    "name": "Nike Total 90 SE",
    "price": "119,99 €",
    "image": null,
    "link": "https://www.nike.com/fr/t/chaussure-total-90-se-pour-TBcVZu0k/IB4204-100",
    "brand": "Nike"
  },
  {
    "name": "Nike V5 RNR",
    "price": "84,99 €",
    "image": null,
    "link": "https://www.nike.com/fr/t/chaussure-v5-rnr-pour-a346k8EB/HQ7901-104",
    "brand": "Nike"
  },
  {
    "name": "Nike Court Vision Low Next Nature",
    "price": "79,99 €",
    "image": null,
    "link": "https://www.nike.com/fr/t/chaussure-court-vision-low-next-nature-pour-sYoDSN1y/DH3158-102",
    "brand": "Nike"
  },
  {
    "name": "Nike Air Force 1 '07 LX",
    "price": "129,99 €",
    "image": null,
    "link": "https://www.nike.com/fr/t/chaussures-air-force-1-07-lx-pour-xLl2Z5oq/DD1525-100",
    "brand": "Nike"
  },
  {
    "name": "Nike Initiator",
    "price": "79,99 €",
    "image": null,
    "link": "https://www.nike.com/fr/t/chaussure-initiator-pour-dwADONaN/FQ6873-101",
    "brand": "Nike"
  },
  {
    "name": "Nike Air Force 1 '07 LV8",
    "price": "129,99 €",
    "image": null,
    "link": "https://www.nike.com/fr/t/chaussures-air-force-1-07-lv8-pour-tqdd1CNt/IH2034-010",
    "brand": "Nike"
  },
  {
    "name": "Nike Initiator",
    "price": "79,99 €",
    "image": null,
    "link": "https://www.nike.com/fr/t/chaussure-initiator-pour-cxYaoJTy/IB4688-111",
    "brand": "Nike"
  },
  {
    "name": "Nike Initiator",
    "price": "79,99 €",
    "image": null,
    "link": "https://www.nike.com/fr/t/chaussure-initiator-pour-Wi3Rru1a/394053-100",
    "brand": "Nike"
  },
  {
    "name": "Nike P-6000",
    "price": "119,99 €",
    "image": null,
    "link": "https://www.nike.com/fr/t/chaussure-p-6000-pour-C1h8I1kJ/FV0943-001",
    "brand": "Nike"
  },
  {
    "name": "Nike V5 RNR",
    "price": "84,99 €",
    "image": null,
    "link": "https://www.nike.com/fr/t/chaussure-v5-rnr-pour-679pATs7/IF2330-001",
    "brand": "Nike"
  },
  {
    "name": "Nike Air Force 1 '07",
    "price": "119,99 €",
    "image": null,
    "link": "https://www.nike.com/fr/t/chaussure-air-force-1-07-pour-iXLENytb/DD8959-100",
    "brand": "Nike"
  },
  {
    "name": "Nike Air Force 1 Low Premium",
    "price": "129,99 €",
    "image": null,
    "link": "https://www.nike.com/fr/t/chaussure-air-force-1-low-pour-XINoFi8n/DN5463-100",
    "brand": "Nike"
  },
  {
    "name": "Nike Initiator",
    "price": "79,99 €",
    "image": null,
    "link": "https://www.nike.com/fr/t/chaussure-initiator-pour-k3VdrLv7/IB4339-001",
    "brand": "Nike"
  },
  {
    "name": "Nike Field General",
    "price": "99,99 €",
    "image": null,
    "link": "https://www.nike.com/fr/t/chaussure-field-general-pour-i9iyIY0s/HJ6000-200",
    "brand": "Nike"
  },
  {
    "name": "Nike Zoom Vomero 5",
    "price": "159,99 €",
    "image": null,
    "link": "https://www.nike.com/fr/t/chaussure-zoom-vomero-5-pour-3A7Bz6Mx/FJ2028-107",
    "brand": "Nike"
  },
  {
    "name": "Nike Bella 7",
    "price": "89,99 €",
    "image": null,
    "link": "https://www.nike.com/fr/t/chaussure-dentrainement-bella-7-pour-o4CtnvqM/FZ1689-004",
    "brand": "Nike"
  },
  {
    "name": "Nike Air Max 90",
    "price": "159,99 €",
    "image": null,
    "link": "https://www.nike.com/fr/t/chaussure-air-max-90-pour-uljZuxTP/IF1619-102",
    "brand": "Nike"
  },
  {
    "name": "Nike Dunk Low",
    "price": "119,99 €",
    "image": null,
    "link": "https://www.nike.com/fr/t/chaussure-dunk-low-pour-GSzNsPwt/II7651-133",
    "brand": "Nike"
  },
  {
    "name": "Air Jordan 1 Low Method of Make",
    "price": "134,99 €",
    "image": null,
    "link": "https://www.nike.com/fr/t/chaussure-air-jordan-1-low-method-of-make-pour-gH5L3GPk/HQ2186-002",
    "brand": "Nike"
  },
  {
    "name": "Nike Dunk Low Retro Premium",
    "price": "129,99 €",
    "image": null,
    "link": "https://www.nike.com/fr/launch/r/IM3077-600",
    "brand": "Nike"
  },
  {
    "name": "Nike Downshifter 13",
    "price": "69,99 €",
    "image": null,
    "link": "https://www.nike.com/fr/t/chaussure-de-running-sur-route-downshifter-13-pour-bmLUjTih/FD6476-001",
    "brand": "Nike"
  },
  {
    "name": "Nike Metcon 10",
    "price": "139,99 €",
    "image": null,
    "link": "https://www.nike.com/fr/t/chaussure-dentrainement-metcon-10-pour-h9VkkPqO/HQ2620-602",
    "brand": "Nike"
  },
  {
    "name": "Nike Zoom Vomero 5",
    "price": "159,99 €",
    "image": null,
    "link": "https://www.nike.com/fr/t/chaussure-zoom-vomero-5-pour-p4VX5t8S/FD0884-025",
    "brand": "Nike"
  },
  {
    "name": "Nike Vomero 18",
    "price": "149,99 €",
    "image": null,
    "link": "https://www.nike.com/fr/t/chaussure-de-running-sur-route-vomero-18-pour-ahnxGXgc/HM6804-603",
    "brand": "Nike"
  },
  {
    "name": "Nike Revolution 8",
    "price": "64,99 €",
    "image": null,
    "link": "https://www.nike.com/fr/t/chaussure-de-running-sur-route-revolution-8-pour-vE06KNsf/HJ8485-002",
    "brand": "Nike"
  },
  {
    "name": "Air Jordan 4 Retro « Worn Blue »",
    "price": "209,99 €",
    "image": null,
    "link": "https://www.nike.com/fr/t/chaussure-air-jordan-4-retro-worn-blue-pour-7sDqY8G8/IB6716-100",
    "brand": "Nike"
  },
  {
    "name": "Nike Air Force 1 '07 EasyOn",
    "price": "119,99 €",
    "image": null,
    "link": "https://www.nike.com/fr/t/chaussure-air-force-1-07-easyon-pour-pP9BS4KJ/DX5883-100",
    "brand": "Nike"
  },
  {
    "name": "Nike Air Force 1 '07",
    "price": "139,99 €",
    "image": null,
    "link": "https://www.nike.com/fr/t/chaussure-air-force-1-07-pour-MlyR7392/IB7695-200",
    "brand": "Nike"
  },
  {
    "name": "Nike Air Force 1 '07",
    "price": "129,99 €",
    "image": null,
    "link": "https://www.nike.com/fr/t/chaussure-air-force-1-07-pour-HFrj6BDK/IH3204-100",
    "brand": "Nike"
  },
  {
    "name": "Nike Air Force 1 Shadow",
    "price": "129,99 €",
    "image": null,
    "link": "https://www.nike.com/fr/t/chaussure-air-force-1-shadow-pour-1TNBqJ7A/CI0919-100",
    "brand": "Nike"
  },
  {
    "name": "Nike Zoom Vomero 5 SE",
    "price": "159,99 €",
    "image": null,
    "link": "https://www.nike.com/fr/t/chaussure-zoom-vomero-5-se-pour-KqbCizZW/IB4397-100",
    "brand": "Nike"
  },
  {
    "name": "Nike Dunk Low « Denim »",
    "price": "129,99 €",
    "image": null,
    "link": "https://www.nike.com/fr/t/chaussure-dunk-low-denim-pour-BT9b1N6g/IH5073-006",
    "brand": "Nike"
  },
  {
    "name": "Nike Vomero 18 SE",
    "price": "149,99 €",
    "image": null,
    "link": "https://www.nike.com/fr/t/chaussure-de-running-sur-route-vomero-18-se-pour-KD5OyYKi/HQ2585-800",
    "brand": "Nike"
  },
  {
    "name": "Air Jordan 1 Low SE",
    "price": "139,99 €",
    "image": null,
    "link": "https://www.nike.com/fr/t/chaussure-air-jordan-1-low-se-pour-gL2Yc9Z1/HQ2004-400",
    "brand": "Nike"
  },
  {
    "name": "Nike Air Rift",
    "price": "129,99 €",
    "image": null,
    "link": "https://www.nike.com/fr/t/chaussure-air-rift-pour-tp0VkZ/HF5389-001",
    "brand": "Nike"
  },
  {
    "name": "Nike Air Max Plus",
    "price": "104,99 €",
    "image": null,
    "link": "https://www.nike.com/fr/t/chaussure-air-max-plus-pour-VBbt8P/CD0610-001",
    "brand": "Nike"
  },
  {
    "name": "Nike Dunk Low",
    "price": "94,99 €",
    "image": null,
    "link": "https://www.nike.com/fr/t/chaussure-dunk-low-pour-ado-gMm4gR/CW1590-100",
    "brand": "Nike"
  },
  {
    "name": "Air Jordan 4 Retro « Cave Stone and Black »",
    "price": "149,99 €",
    "image": null,
    "link": "https://www.nike.com/fr/t/chaussure-air-jordan-4-retro-cave-stone-and-black-pour-ado-shPKqN/IB4171-200",
    "brand": "Nike"
  },
  {
    "name": "Nike Dunk Low x LEGO® Collection",
    "price": "104,99 €",
    "image": null,
    "link": "https://www.nike.com/fr/t/chaussure-dunk-low-lego-collection-pour-ado-fuzYfTa3/IF2117-100",
    "brand": "Nike"
  },
  {
    "name": "Nike Ava Rover",
    "price": "139,99 €",
    "image": null,
    "link": "https://www.nike.com/fr/t/chaussure-ava-rover-lJnNmF/DX4215-003",
    "brand": "Nike"
  },
  {
    "name": "Jordan 4 Retro « Cave Stone and Black »",
    "price": "89,99 €",
    "image": null,
    "link": "https://www.nike.com/fr/t/chaussure-jordan-4-retro-cave-stone-and-black-pour-tV5wM9/IB4388-200",
    "brand": "Nike"
  },
  {
    "name": "Nike Air Force 1",
    "price": "99,99 €",
    "image": null,
    "link": "https://www.nike.com/fr/t/chaussure-air-force-1-pour-ado-HjXjwqHQ/FV5948-101",
    "brand": "Nike"
  },
  {
    "name": "Nike Dunk Low",
    "price": "69,99 €",
    "image": null,
    "link": "https://www.nike.com/fr/t/chaussure-dunk-low-pour-jeune-7mb4ZM/CW1588-100",
    "brand": "Nike"
  },
  {
    "name": "Air Jordan 1 Low SE",
    "price": "99,99 €",
    "image": null,
    "link": "https://www.nike.com/fr/t/chaussure-air-jordan-1-low-se-pour-ado-wrd5nlfM/HQ2001-400",
    "brand": "Nike"
  },
  {
    "name": "Nike Air Max Dn",
    "price": "104,99 €",
    "image": null,
    "link": "https://www.nike.com/fr/t/chaussure-air-max-dn-pour-5WFk3Zvn/IH7673-600",
    "brand": "Nike"
  },
  {
    "name": "Nike Vomero 5",
    "price": "114,99 €",
    "image": null,
    "link": "https://www.nike.com/fr/t/chaussure-vomero-5-pour-ado-yiO6eTmX/IB5853-002",
    "brand": "Nike"
  },
  {
    "name": "Nike Air Force 1 '07",
    "price": "119,99 €",
    "image": null,
    "link": "https://www.nike.com/fr/t/chaussure-air-force-1-07-pour-iXLENytb/DD8959-001",
    "brand": "Nike"
  },
  {
    "name": "Nike Air Max 90 EasyOn",
    "price": "84,99 €",
    "image": null,
    "link": "https://www.nike.com/fr/t/chaussure-air-max-90-easyon-pour-tDH0VG/IH1417-300",
    "brand": "Nike"
  },
  {
    "name": "Nike Air Max 95 Recraft",
    "price": "99,99 €",
    "image": null,
    "link": "https://www.nike.com/fr/t/chaussure-air-max-95-recraft-pour-pqeoG8Zd/HQ6364-001",
    "brand": "Nike"
  },
  {
    "name": "Nike Air Max Plus",
    "price": "139,99 €",
    "image": null,
    "link": "https://www.nike.com/fr/t/chaussure-air-max-plus-pour-ado-Pa1GB9cu/IF6167-700",
    "brand": "Nike"
  },
  {
    "name": "Nike Force 1 Low EasyOn",
    "price": "69,99 €",
    "image": null,
    "link": "https://www.nike.com/fr/t/chaussure-force-1-low-easyon-pour-HdQtoC8p/IH4498-101",
    "brand": "Nike"
  },
  {
    "name": "Nike Dunk Low x LEGO® Collection",
    "price": "79,99 €",
    "image": null,
    "link": "https://www.nike.com/fr/t/chaussure-dunk-low-lego-collection-pour-MnoXDo8i/II7288-100",
    "brand": "Nike"
  },
  {
    "name": "Nike Air Max Plus",
    "price": "104,99 €",
    "image": null,
    "link": "https://www.nike.com/fr/t/chaussure-air-max-plus-pour-Me2ZCNF4/FZ0023-700",
    "brand": "Nike"
  }
]
